outgen/__init__.py
outgen/main.py
outgen-0.1.0.dist-info/METADATA
outgen-0.1.0.dist-info/WHEEL
outgen-0.1.0.dist-info/licenses/LICENSE
outgen-0.1.0.dist-info/RECORD
